django_handy_admin/__init__.py
django_handy_admin/templates/admin/index.html
django_handy_admin-0.0.0.dist-info/LICENSE
django_handy_admin-0.0.0.dist-info/WHEEL
django_handy_admin-0.0.0.dist-info/METADATA
django_handy_admin-0.0.0.dist-info/RECORD
