Metadata-Version: 2.1
Name: django-handy-admin
Version: 0.0.0
Summary: Set of handy addons to Django Admin.
Author: Michał Sut
Author-email: sut.michal@gmail.com
Requires-Python: >=3.8,<4.0
Classifier: Programming Language :: Python :: 3
Classifier: Programming Language :: Python :: 3.8
Classifier: Programming Language :: Python :: 3.9
Classifier: Programming Language :: Python :: 3.10
Classifier: Programming Language :: Python :: 3.11
Requires-Dist: django (==4.2)
